{
  "updated_at": "2026-04-08T13:48:27.346126",
  "news": {
    "ap": [],
    "npr": [
      {
        "title": "Oil prices plunge and stocks soar after U.S. and Iran agree on ceasefire",
        "link": "https://www.npr.org/2026/04/08/nx-s1-5776818/wall-street-stocks-oil-trump-iran-ceasefire",
        "pubDate": "Wed, 08 Apr 2026 09:33:28 -0400",
        "category": "world"
      },
      {
        "title": "U.S., Iran agree to 2-week ceasefire. And, Trump-backed Clay Fuller wins House race",
        "link": "https://www.npr.org/2026/04/08/g-s1-116752/up-first-newsletter-iran-trump-israel-ceasefire-clay-fuller-ice-spyware-telehealth-abortions",
        "pubDate": "Wed, 08 Apr 2026 07:55:39 -0400",
        "category": "Top News"
      },
      {
        "title": "Colleges are trying to boost student voting. A Trump probe freezes data for that work",
        "link": "https://www.npr.org/2026/04/08/nx-s1-5725279/college-trump-voting-data-probe-voting-registration",
        "pubDate": "Wed, 08 Apr 2026 05:00:00 -0400",
        "category": "us"
      },
      {
        "title": "Abortion clinics are closing nationwide. Could urgent care help fill the gap?",
        "link": "https://www.npr.org/2026/04/08/nx-s1-5773333/planned-parenthood-urgent-care-medication-abortion-rural",
        "pubDate": "Wed, 08 Apr 2026 05:00:00 -0400",
        "category": "health"
      },
      {
        "title": "Your sarcasm is showing \u2014 and its history is surprisingly violent",
        "link": "https://www.npr.org/2026/04/08/nx-s1-5771648/sarcasm-origin-history-etymology",
        "pubDate": "Wed, 08 Apr 2026 05:00:00 -0400",
        "category": "Top News"
      },
      {
        "title": "Morning news brief",
        "link": "https://www.npr.org/2026/04/08/nx-s1-5775826/morning-news-brief",
        "pubDate": "Wed, 08 Apr 2026 04:46:50 -0400",
        "category": "Top News"
      },
      {
        "title": "The U.S. and Iran agree to a 2-week ceasefire",
        "link": "https://www.npr.org/2026/04/08/nx-s1-5777291/iran-war-updates",
        "pubDate": "Wed, 08 Apr 2026 03:55:01 -0400",
        "category": "Top News"
      },
      {
        "title": "Telehealth abortion will remain available for now, after a federal judge&apos;s ruling",
        "link": "https://www.npr.org/2026/04/07/nx-s1-5776946/telehealth-abortion-louisiana-federal-court-mifepristone",
        "pubDate": "Tue, 07 Apr 2026 21:52:15 -0400",
        "category": "Top News"
      },
      {
        "title": "ICE acknowledges it is using powerful spyware",
        "link": "https://www.npr.org/2026/04/07/nx-s1-5776799/ice-spyware-privacy",
        "pubDate": "Tue, 07 Apr 2026 17:01:24 -0400",
        "category": "tech"
      },
      {
        "title": "Drive slower, go electric, don&apos;t drive at all? Americans weigh options for saving gas",
        "link": "https://www.npr.org/2026/04/07/nx-s1-5775907/high-gas-prices-save-money-iran-war",
        "pubDate": "Tue, 07 Apr 2026 12:00:00 -0400",
        "category": "business"
      }
    ],
    "bbc": [
      {
        "title": "Israel carries out large wave of air strikes across Lebanon",
        "link": "https://www.bbc.com/news/articles/c0j6d538l6qo?at_medium=RSS&amp;at_campaign=rss",
        "pubDate": "Wed, 08 Apr 2026 13:13:46 GMT",
        "category": "Top News"
      },
      {
        "title": "Faisal Islam: Iran war pause is welcome but the economic scars will last",
        "link": "https://www.bbc.com/news/articles/c5yx4e9d8pdo?at_medium=RSS&amp;at_campaign=rss",
        "pubDate": "Wed, 08 Apr 2026 12:44:15 GMT",
        "category": "business"
      },
      {
        "title": "Faisal Islam: Pause in attacks is welcome but the economic scars will last",
        "link": "https://www.bbc.com/news/articles/c5yx4e9d8pdo?at_medium=RSS&amp;at_campaign=rss",
        "pubDate": "Wed, 08 Apr 2026 12:44:15 GMT",
        "category": "Top News"
      },
      {
        "title": "What we know about the two-week ceasefire between the US and Iran",
        "link": "https://www.bbc.com/news/articles/ce84z6y3ke4o?at_medium=RSS&amp;at_campaign=rss",
        "pubDate": "Wed, 08 Apr 2026 12:36:05 GMT",
        "category": "Top News"
      },
      {
        "title": "Watch: When will fuel prices go down?",
        "link": "https://www.bbc.com/news/videos/c62je685v3vo?at_medium=RSS&amp;at_campaign=rss",
        "pubDate": "Wed, 08 Apr 2026 11:23:35 GMT",
        "category": "Top News"
      },
      {
        "title": "Hospitals coping well with doctors' strike so far - NHS boss",
        "link": "https://www.bbc.com/news/articles/clyrzrp0x5go?at_medium=RSS&amp;at_campaign=rss",
        "pubDate": "Wed, 08 Apr 2026 10:56:27 GMT",
        "category": "health"
      },
      {
        "title": "Brit says he is not elusive Bitcoin creator named by New York Times",
        "link": "https://www.bbc.com/news/articles/cgrl4l1y9yxo?at_medium=RSS&amp;at_campaign=rss",
        "pubDate": "Wed, 08 Apr 2026 10:33:54 GMT",
        "category": "tech"
      },
      {
        "title": "Oil prices plunge and shares jump on US-Iran ceasefire plan",
        "link": "https://www.bbc.com/news/articles/c8r40y3rv75o?at_medium=RSS&amp;at_campaign=rss",
        "pubDate": "Wed, 08 Apr 2026 08:15:36 GMT",
        "category": "us"
      },
      {
        "title": "Iran ceasefire deal gives Trump a way out of war - but at a high cost",
        "link": "https://www.bbc.com/news/articles/cwyvp55xrlro?at_medium=RSS&amp;at_campaign=rss",
        "pubDate": "Wed, 08 Apr 2026 03:30:55 GMT",
        "category": "world"
      },
      {
        "title": "Iran deal gives Trump a way out of war - but at a high cost",
        "link": "https://www.bbc.com/news/articles/cwyvp55xrlro?at_medium=RSS&amp;at_campaign=rss",
        "pubDate": "Wed, 08 Apr 2026 03:30:55 GMT",
        "category": "Top News"
      }
    ],
    "reuters": [
      {
        "title": "World Bank says South Asia growth to slow to 6.3% in 2026 amid Middle East conflict",
        "link": "http://www.bing.com/news/apiclick.aspx?ref=FexRss&amp;aid=&amp;tid=69d65c48b1fd4f12853c6b7c6c7fcc70&amp;url=https%3a%2f%2fwww.reuters.com%2fworld%2fasia-pacific%2fworld-bank-says-south-asia-growth-slow-63-2026-amid-middle-east-conflict-2026-04-08%2f&amp;c=8893821810867420966&amp;mkt=en-us",
        "pubDate": "Wed, 08 Apr 2026 05:09:00 GMT",
        "category": "world"
      },
      {
        "title": "Britain picks business leader Ian Cheshire to chair media regulator",
        "link": "http://www.bing.com/news/apiclick.aspx?ref=FexRss&amp;aid=&amp;tid=69d65c5bd43343d3a6b61cd4e5bca212&amp;url=https%3a%2f%2fwww.reuters.com%2fworld%2fuk%2fbritain-picks-business-leader-ian-cheshire-chair-media-regulator-2026-04-08%2f&amp;c=6197323983903965301&amp;mkt=en-us",
        "pubDate": "Wed, 08 Apr 2026 03:49:00 GMT",
        "category": "business"
      },
      {
        "title": "China's Sigenergy Technology aims to raise $562 mln in Hong Kong IPO",
        "link": "http://www.bing.com/news/apiclick.aspx?ref=FexRss&amp;aid=&amp;tid=69d65c5d3b5b463695e2a163857e042f&amp;url=https%3a%2f%2fwww.reuters.com%2fworld%2fasia-pacific%2fchinas-sigenergy-technology-aims-raise-562-mln-hong-kong-ipo-2026-04-07%2f&amp;c=3053425868050786331&amp;mkt=en-us",
        "pubDate": "Tue, 07 Apr 2026 15:13:00 GMT",
        "category": "tech"
      }
    ],
    "markets": []
  }
}