{
  "updated_at": "2026-01-18T16:33:51.610551",
  "news": {
    "ap": [
      {
        "title": "Today in Sports - Lindsey Vonn wins a record 63rd World Cup victory, stood for 35-years",
        "link": "http://www.bing.com/news/apiclick.aspx?ref=FexRss&amp;aid=&amp;tid=696d0ae0f84445b1bc5bba4a8fddb3b4&amp;url=https%3a%2f%2fapnews.com%2farticle%2flindsey-vonn-denis-istomin-novak-djokovic-san-francisco-49ers-213a60caf70d260fe84c53ff5de64b55&amp;c=1807492663245901437&amp;mkt=en-us",
        "pubDate": "Sun, 18 Jan 2026 07:10:00 GMT",
        "category": "world"
      },
      {
        "title": "Social media addiction\u2019s surprising challenger? Anti-doomscrolling influencers",
        "link": "http://www.bing.com/news/apiclick.aspx?ref=FexRss&amp;aid=&amp;tid=696d0af059844502b72c11646ba60429&amp;url=https%3a%2f%2fapnews.com%2farticle%2fsocial-media-addiction-screen-time-a50f6def00a5723ba61e0a78ba761669&amp;c=361944949372335848&amp;mkt=en-us",
        "pubDate": "Sat, 17 Jan 2026 22:00:00 GMT",
        "category": "business"
      }
    ],
    "npr": [
      {
        "title": "U.S. military troops on standby for possible deployment to Minnesota",
        "link": "https://www.npr.org/2026/01/18/nx-s1-5681372/u-s-military-troops-on-standby-for-possible-deployment-to-minnesota",
        "pubDate": "Sun, 18 Jan 2026 10:34:08 -0500",
        "category": "us"
      },
      {
        "title": "Martin Luther King Jr. had a dream ... about health care",
        "link": "https://www.npr.org/2026/01/18/g-s1-106127/martin-luther-king-jr-dream-health-care",
        "pubDate": "Sun, 18 Jan 2026 10:22:19 -0500",
        "category": "health"
      },
      {
        "title": "Venezuela: Maduro&apos;s enforcer Cabello still central to power",
        "link": "https://www.npr.org/2026/01/18/nx-s1-5678974/venezuela-maduro-enforcer-cabello",
        "pubDate": "Sun, 18 Jan 2026 06:00:00 -0500",
        "category": "world"
      },
      {
        "title": "Amid ICE clashes, New Hampshire bishop urges clergy to prepare their wills",
        "link": "https://www.npr.org/2026/01/18/nx-s1-5678579/ice-clashes-new-hampshire-bishop-urges-clergy-prepare-wills",
        "pubDate": "Sun, 18 Jan 2026 05:00:00 -0500",
        "category": "Top News"
      },
      {
        "title": "New York Giants hire John Harbaugh as coach after identifying him as their top choice",
        "link": "https://www.npr.org/2026/01/17/g-s1-106420/harbaugh-ny-giants-coach-ravens",
        "pubDate": "Sat, 17 Jan 2026 19:40:04 -0500",
        "category": "Top News"
      },
      {
        "title": "US launches new retaliatory strike in Syria, killing leader tied to deadly Islamic State ambush",
        "link": "https://www.npr.org/2026/01/17/g-s1-106418/us-strike-syria-islamic-state-ambush",
        "pubDate": "Sat, 17 Jan 2026 17:09:12 -0500",
        "category": "Top News"
      },
      {
        "title": "NASA&apos;s Artemis II craft meets the launch pad ahead of crewed lunar orbit",
        "link": "https://www.npr.org/2026/01/17/g-s1-106406/nasa-rolls-out-artemis-ii",
        "pubDate": "Sat, 17 Jan 2026 14:12:56 -0500",
        "category": "Top News"
      },
      {
        "title": "Trump says 8 EU countries to be charged 10% tariff for opposing US control of Greenland",
        "link": "https://www.npr.org/2026/01/17/nx-s1-5680839/trump-eu-greenland-tariffs",
        "pubDate": "Sat, 17 Jan 2026 12:22:48 -0500",
        "category": "Top News"
      },
      {
        "title": "&apos;Not for sale&apos;: massive protest in Copenhagen against Trump&apos;s desire to acquire Greenland",
        "link": "https://www.npr.org/2026/01/17/g-s1-106401/not-for-sale-massive-protest-in-copenhagen-against-trumps-desire-to-acquire-greenland",
        "pubDate": "Sat, 17 Jan 2026 12:00:35 -0500",
        "category": "Top News"
      }
    ],
    "bbc": [
      {
        "title": "Greenland's people must decide its future, says Nandy",
        "link": "https://www.bbc.com/news/articles/cwyn90l1dneo?at_medium=RSS&amp;at_campaign=rss",
        "pubDate": "Sun, 18 Jan 2026 15:32:29 GMT",
        "category": "Top News"
      },
      {
        "title": "Minister 'confident' issues over Hillsborough Law can be resolved",
        "link": "https://www.bbc.com/news/articles/c5yvldj47v9o?at_medium=RSS&amp;at_campaign=rss",
        "pubDate": "Sun, 18 Jan 2026 13:28:25 GMT",
        "category": "Top News"
      },
      {
        "title": "Reform is not rescue charity for panicky Tory MPs, Farage says",
        "link": "https://www.bbc.com/news/articles/c4gv9gyxgjjo?at_medium=RSS&amp;at_campaign=rss",
        "pubDate": "Sun, 18 Jan 2026 11:27:19 GMT",
        "category": "Top News"
      },
      {
        "title": "Fears Iran's internet shutdown could lead to 'extreme digital isolation'",
        "link": "https://www.bbc.com/news/articles/cg5gegrdq3go?at_medium=RSS&amp;at_campaign=rss",
        "pubDate": "Sun, 18 Jan 2026 11:09:29 GMT",
        "category": "world"
      },
      {
        "title": "Around 1,500 soldiers on standby for deployment to Minneapolis, officials say",
        "link": "https://www.bbc.com/news/articles/c74v0pxg2nvo?at_medium=RSS&amp;at_campaign=rss",
        "pubDate": "Sun, 18 Jan 2026 07:28:47 GMT",
        "category": "us"
      },
      {
        "title": "Mum thanks strangers who rescued nine-month-old baby from burning car",
        "link": "https://www.bbc.com/news/articles/cvgjvrggnvno?at_medium=RSS&amp;at_campaign=rss",
        "pubDate": "Sun, 18 Jan 2026 07:27:59 GMT",
        "category": "Top News"
      },
      {
        "title": "Faisal Islam: Trump's Greenland threats to allies are without parallel",
        "link": "https://www.bbc.com/news/articles/cx2gjdx241wo?at_medium=RSS&amp;at_campaign=rss",
        "pubDate": "Sun, 18 Jan 2026 06:38:17 GMT",
        "category": "business"
      },
      {
        "title": "I want to show what Africa is - YouTube star IShowSpeed brings joy and tears on tour",
        "link": "https://www.bbc.com/news/articles/c5y5le7yl7po?at_medium=RSS&amp;at_campaign=rss",
        "pubDate": "Sun, 18 Jan 2026 00:21:02 GMT",
        "category": "Top News"
      },
      {
        "title": "Gangland killing at a funeral shocks idyllic French island",
        "link": "https://www.bbc.com/news/articles/c620nq38y6po?at_medium=RSS&amp;at_campaign=rss",
        "pubDate": "Sun, 18 Jan 2026 00:08:38 GMT",
        "category": "Top News"
      },
      {
        "title": "A deadly fire swept through a nightclub in just 90 seconds. I got out",
        "link": "https://www.bbc.com/news/articles/czejykzg77po?at_medium=RSS&amp;at_campaign=rss",
        "pubDate": "Sun, 18 Jan 2026 00:08:10 GMT",
        "category": "Top News"
      }
    ],
    "reuters": [
      {
        "title": "World markets face fresh jolt as Trump vows tariffs on Europe over Greenland",
        "link": "http://www.bing.com/news/apiclick.aspx?ref=FexRss&amp;aid=&amp;tid=696d0b12d57948cbbd7c82e47877540d&amp;url=https%3a%2f%2fwww.reuters.com%2fworld%2feurope%2fworld-markets-face-fresh-jolt-trump-vows-tariffs-europe-over-greenland-2026-01-18%2f&amp;c=1092883349403638201&amp;mkt=en-us",
        "pubDate": "Sun, 18 Jan 2026 05:36:00 GMT",
        "category": "world"
      }
    ],
    "markets": [
      {
        "title": "&apos;Unacceptable&apos;: European leaders hit back at Trump&apos;s Greenland tariffs threat",
        "link": "https://www.cnbc.com/2026/01/18/european-leaders-reaction-trump-greenland-tariffs-threat.html",
        "pubDate": "Sun, 18 Jan 2026 13:58:32 GMT",
        "category": "world"
      }
    ]
  }
}