{
  "updated_at": "2025-12-29T04:53:57.366364",
  "news": {
    "ap": [
      {
        "title": "Shaw and Saint Mary\u2019s take down Loyola Marymount 78-73",
        "link": "http://www.bing.com/news/apiclick.aspx?ref=FexRss&amp;aid=&amp;tid=6952095336614a75a297a9bb853a9d20&amp;url=https%3a%2f%2fapnews.com%2farticle%2frory-hawke-saint-marys-gaels-loyola-marymount-lions-college-basketball-college-sports-aef0fdd0ef68422cb4dcf3c37e94b32d&amp;c=9736270213497946384&amp;mkt=en-us",
        "pubDate": "Sun, 28 Dec 2025 19:36:00 GMT",
        "category": "tech"
      },
      {
        "title": "Pipe bomb suspect told FBI he targeted US political parties because they were \u2018in charge,\u2019 memo says",
        "link": "http://www.bing.com/news/apiclick.aspx?ref=FexRss&amp;aid=&amp;tid=6952094407634b7ea61bac4e27bd26bd&amp;url=https%3a%2f%2fapnews.com%2farticle%2fpipe-bomb-jan-6-fbi-157854dadb81c4d7663553412fd19383&amp;c=18288766857324736809&amp;mkt=en-us",
        "pubDate": "Sun, 28 Dec 2025 17:07:00 GMT",
        "category": "us"
      },
      {
        "title": "Winter rain floods Gaza camps as Netanyahu heads for US meeting",
        "link": "http://www.bing.com/news/apiclick.aspx?ref=FexRss&amp;aid=&amp;tid=69520954b31a40df9be883293bd096d6&amp;url=https%3a%2f%2fapnews.com%2farticle%2fisrael-hamas-gaza-rain-flooding-camps-03427b994adfb84a6d5f4a49d440d5ae&amp;c=15101245071857080938&amp;mkt=en-us",
        "pubDate": "Sun, 28 Dec 2025 13:30:00 GMT",
        "category": "health"
      },
      {
        "title": "Mikaela Shiffrin keeps World Cup slalom streak going but slams course conditions in night race",
        "link": "http://www.bing.com/news/apiclick.aspx?ref=FexRss&amp;aid=&amp;tid=695209433ffb4524802b70ad35e3bd4f&amp;url=https%3a%2f%2fapnews.com%2farticle%2falpine-skiing-olympics-slalom-austria-shiffrin-a1bb23c13ce4aa629409ecaf4f5c5ec6&amp;c=8376278871754391865&amp;mkt=en-us",
        "pubDate": "Sun, 28 Dec 2025 11:45:00 GMT",
        "category": "world"
      }
    ],
    "npr": [
      {
        "title": "Do Trump&apos;s claims about Christian persecution in Nigeria match reality?",
        "link": "https://www.npr.org/2025/12/28/nx-s1-5659769/do-trumps-claims-about-christian-persecution-in-nigeria-match-reality",
        "pubDate": "Sun, 28 Dec 2025 17:26:43 -0500",
        "category": "world"
      },
      {
        "title": "&apos;Bomb cyclone&apos; forecasted to bring heavy snow, blizzard conditions and dangerous travel",
        "link": "https://www.npr.org/2025/12/28/nx-s1-5659746/bomb-cyclone-blizzard-dangerous-travel",
        "pubDate": "Sun, 28 Dec 2025 15:28:37 -0500",
        "category": "us"
      },
      {
        "title": "Russia sends 3 Iranian satellites into orbit, report says",
        "link": "https://www.npr.org/2025/12/28/nx-s1-5659773/russia-iranian-satellites",
        "pubDate": "Sun, 28 Dec 2025 12:55:11 -0500",
        "category": "Top News"
      },
      {
        "title": "Viral global TikToks: A twist on soccer, Tanzania&apos;s Charlie Chaplin, hope in Gaza",
        "link": "https://www.npr.org/sections/goats-and-soda/2025/12/28/g-s1-103034/tiktok-gaza-africa-brazil-soccer-history-charlie-chaplin",
        "pubDate": "Sun, 28 Dec 2025 08:25:04 -0500",
        "category": "health"
      },
      {
        "title": "The year in AI and culture",
        "link": "https://www.npr.org/2025/12/28/nx-s1-5653367/the-year-in-ai-and-culture",
        "pubDate": "Sun, 28 Dec 2025 08:05:28 -0500",
        "category": "tech"
      },
      {
        "title": "Memory loss: As AI gobbles up chips, prices for devices may rise",
        "link": "https://www.npr.org/2025/12/28/nx-s1-5656190/ai-chips-memory-prices-ram",
        "pubDate": "Sun, 28 Dec 2025 06:00:00 -0500",
        "category": "business"
      },
      {
        "title": "Brigitte Bardot, sex goddess of cinema, has died",
        "link": "https://www.npr.org/2025/12/28/1130645838/brigitte-bardot-dead",
        "pubDate": "Sun, 28 Dec 2025 05:52:56 -0500",
        "category": "Top News"
      },
      {
        "title": "For Ukrainians, a nuclear missile museum is a bitter reminder of what the country gave up",
        "link": "https://www.npr.org/2025/12/28/g-s1-103485/ukraine-museum-strategic-missile-forces-budapest-agreement",
        "pubDate": "Sun, 28 Dec 2025 05:02:00 -0500",
        "category": "Top News"
      },
      {
        "title": "Trump says Ukraine and Russia &apos;closer than ever&apos; to peace after talks with Zelenskyy",
        "link": "https://www.npr.org/2025/12/28/nx-s1-5659700/zelenskyy-meets-trump-efforts-end-russia-ukraine-war-elusive",
        "pubDate": "Sun, 28 Dec 2025 03:25:09 -0500",
        "category": "Top News"
      }
    ],
    "bbc": [
      {
        "title": "Egyptian dissident sorry for tweets as Tories push for deportation from UK",
        "link": "https://www.bbc.com/news/articles/c0l93lx1rx3o?at_medium=RSS&amp;at_campaign=rss",
        "pubDate": "Mon, 29 Dec 2025 04:44:56 GMT",
        "category": "Top News"
      },
      {
        "title": "2026 will have some of the best TV in years - here are the highlights",
        "link": "https://www.bbc.com/news/articles/c9qedx5wj45o?at_medium=RSS&amp;at_campaign=rss",
        "pubDate": "Mon, 29 Dec 2025 04:27:06 GMT",
        "category": "Top News"
      },
      {
        "title": "China holds military drills around Taiwan as warning to 'separatist forces'",
        "link": "https://www.bbc.com/news/articles/c87l7xjp235o?at_medium=RSS&amp;at_campaign=rss",
        "pubDate": "Mon, 29 Dec 2025 04:14:11 GMT",
        "category": "world"
      },
      {
        "title": "John Simpson: 'I've reported on 40 wars but I've never seen a year like 2025'",
        "link": "https://www.bbc.com/news/articles/cj4qp17e1lqo?at_medium=RSS&amp;at_campaign=rss",
        "pubDate": "Mon, 29 Dec 2025 03:03:56 GMT",
        "category": "Top News"
      },
      {
        "title": "Trump says progress made in Ukraine talks but 'thorny issues' remain",
        "link": "https://www.bbc.com/news/articles/c36z615y443o?at_medium=RSS&amp;at_campaign=rss",
        "pubDate": "Mon, 29 Dec 2025 02:06:51 GMT",
        "category": "us"
      },
      {
        "title": "Living in fear of Lakurawa - the militant group Trump targeted in Nigeria strikes",
        "link": "https://www.bbc.com/news/articles/cy7vr76l521o?at_medium=RSS&amp;at_campaign=rss",
        "pubDate": "Mon, 29 Dec 2025 01:30:56 GMT",
        "category": "Top News"
      },
      {
        "title": "Trump and Zelensky appear more upbeat - but show little evidence that peace is near for Ukraine",
        "link": "https://www.bbc.com/news/articles/c17x7lnd1r7o?at_medium=RSS&amp;at_campaign=rss",
        "pubDate": "Mon, 29 Dec 2025 01:05:38 GMT",
        "category": "Top News"
      },
      {
        "title": "The words from my dad that saved me as a new parent",
        "link": "https://www.bbc.com/news/articles/crmd80gkwkdo?at_medium=RSS&amp;at_campaign=rss",
        "pubDate": "Mon, 29 Dec 2025 00:03:04 GMT",
        "category": "Top News"
      },
      {
        "title": "Many new UK drone users must take theory test before flying outside",
        "link": "https://www.bbc.com/news/articles/cjrjpzdzeddo?at_medium=RSS&amp;at_campaign=rss",
        "pubDate": "Mon, 29 Dec 2025 00:02:30 GMT",
        "category": "business"
      },
      {
        "title": "Cold weather to ring in New Year as amber health alerts issued",
        "link": "https://www.bbc.com/news/articles/cx25e9yr28go?at_medium=RSS&amp;at_campaign=rss",
        "pubDate": "Sun, 28 Dec 2025 18:06:48 GMT",
        "category": "Top News"
      }
    ],
    "reuters": [
      {
        "title": "Kosovo\u2019s Kurti promises swift formation of new government after election win",
        "link": "http://www.bing.com/news/apiclick.aspx?ref=FexRss&amp;aid=&amp;tid=695209577cc24bcf938392f9aa3812dd&amp;url=https%3a%2f%2fwww.reuters.com%2fworld%2fkosovo-votes-bid-end-year-long-political-impasse-2025-12-28%2f&amp;c=15300452398313446267&amp;mkt=en-us",
        "pubDate": "Sun, 28 Dec 2025 19:41:00 GMT",
        "category": "Top News"
      },
      {
        "title": "China's Leapmotor targets annual sales of more than 4 million units in a decade",
        "link": "http://www.bing.com/news/apiclick.aspx?ref=FexRss&amp;aid=&amp;tid=6952095accb849debcf4ccaa7e4f3e71&amp;url=https%3a%2f%2fwww.reuters.com%2fbusiness%2fautos-transportation%2fchinas-leapmotor-targets-annual-sales-more-than-4-million-units-decade-2025-12-29%2f&amp;c=10491002362497334758&amp;mkt=en-us",
        "pubDate": "Sun, 28 Dec 2025 19:21:00 GMT",
        "category": "tech"
      },
      {
        "title": "South Korean president vows to reveal truth on anniversary of Jeju Air crash",
        "link": "http://www.bing.com/news/apiclick.aspx?ref=FexRss&amp;aid=&amp;tid=695209577cc24bcf938392f9aa3812dd&amp;url=https%3a%2f%2fwww.reuters.com%2fworld%2fasia-pacific%2fsouth-korean-president-vows-reveal-truth-anniversary-jeju-air-crash-2025-12-29%2f&amp;c=15153397042519562583&amp;mkt=en-us",
        "pubDate": "Sun, 28 Dec 2025 17:30:00 GMT",
        "category": "Top News"
      },
      {
        "title": "US Justice Department using fraud law to target companies on DEI, WSJ reports",
        "link": "http://www.bing.com/news/apiclick.aspx?ref=FexRss&amp;aid=&amp;tid=69520959afda47f8b2fad2be90fab53a&amp;url=https%3a%2f%2fwww.reuters.com%2fsustainability%2fsociety-equity%2fus-justice-department-using-fraud-law-target-companies-dei-wsj-reports-2025-12-29%2f&amp;c=13156102360086825368&amp;mkt=en-us",
        "pubDate": "Sun, 28 Dec 2025 17:21:00 GMT",
        "category": "us"
      },
      {
        "title": "Trump, Netanyahu to discuss next phase of Gaza plan",
        "link": "http://www.bing.com/news/apiclick.aspx?ref=FexRss&amp;aid=&amp;tid=6952095cdcca4b92b25f7bfb547b1329&amp;url=https%3a%2f%2fwww.reuters.com%2fworld%2fmiddle-east%2ftrump-netanyahu-discuss-next-phase-gaza-plan-2025-12-28%2f&amp;c=6255814417451898186&amp;mkt=en-us",
        "pubDate": "Sun, 28 Dec 2025 14:07:00 GMT",
        "category": "health"
      },
      {
        "title": "North Korea's Kim Jong Un oversees cruise missile launching drill",
        "link": "http://www.bing.com/news/apiclick.aspx?ref=FexRss&amp;aid=&amp;tid=695209577cc24bcf938392f9aa3812dd&amp;url=https%3a%2f%2fwww.reuters.com%2fbusiness%2faerospace-defense%2fnorth-koreas-kim-jong-un-oversees-long-range-strategic-cruise-missile-launching-2025-12-28%2f&amp;c=12702106977641078482&amp;mkt=en-us",
        "pubDate": "Sun, 28 Dec 2025 13:13:00 GMT",
        "category": "Top News"
      },
      {
        "title": "Shiffrin roars back to win Semmering World Cup slalom",
        "link": "http://www.bing.com/news/apiclick.aspx?ref=FexRss&amp;aid=&amp;tid=6952095813e341a09aeb02515051cd6c&amp;url=https%3a%2f%2fwww.reuters.com%2fsports%2fshiffrin-roars-back-win-semmering-world-cup-slalom-2025-12-28%2f&amp;c=16116200722372220148&amp;mkt=en-us",
        "pubDate": "Sun, 28 Dec 2025 10:48:00 GMT",
        "category": "world"
      },
      {
        "title": "Central African Republic votes, Russia ally Touadera seeks third term",
        "link": "http://www.bing.com/news/apiclick.aspx?ref=FexRss&amp;aid=&amp;tid=695209577cc24bcf938392f9aa3812dd&amp;url=https%3a%2f%2fwww.reuters.com%2fworld%2fafrica%2fcentral-african-republic-votes-russia-ally-touadera-seeks-third-term-2025-12-28%2f&amp;c=7585975424065820453&amp;mkt=en-us",
        "pubDate": "Sun, 28 Dec 2025 09:34:00 GMT",
        "category": "Top News"
      },
      {
        "title": "Kyrgios beats Sabalenka in 'Battle of the Sexes' showdown",
        "link": "http://www.bing.com/news/apiclick.aspx?ref=FexRss&amp;aid=&amp;tid=695209577cc24bcf938392f9aa3812dd&amp;url=https%3a%2f%2fwww.reuters.com%2fsports%2ftennis%2fkyrgios-beats-sabalenka-battle-sexes-showdown-2025-12-28%2f&amp;c=1463215861699289318&amp;mkt=en-us",
        "pubDate": "Sun, 28 Dec 2025 09:22:00 GMT",
        "category": "Top News"
      },
      {
        "title": "Israel's tech sector says more staff seek relocation abroad-report",
        "link": "http://www.bing.com/news/apiclick.aspx?ref=FexRss&amp;aid=&amp;tid=6952095919864d8ea32514bc9c3527d3&amp;url=https%3a%2f%2fwww.reuters.com%2fbusiness%2fworld-at-work%2fisraels-tech-sector-says-more-staff-seek-relocation-abroad-report-2025-12-28%2f&amp;c=9618956820731452675&amp;mkt=en-us",
        "pubDate": "Sun, 28 Dec 2025 06:57:00 GMT",
        "category": "business"
      }
    ],
    "markets": [
      {
        "title": "South Korean retail giant Coupang to compensate $1.1 billion to affected users over data breach",
        "link": "https://www.cnbc.com/2025/12/29/south-korea-retail-coupang-bon-kim-1-billion-trillion-won-data-breach-compensation-vouchers.html",
        "pubDate": "Mon, 29 Dec 2025 02:19:18 GMT",
        "category": "world"
      },
      {
        "title": "Wall Street wrote off Palantir as too expensive. Retail investors can&apos;t get enough",
        "link": "https://www.cnbc.com/2025/12/25/palantir-retail-investors-valuation-karp.html",
        "pubDate": "Sun, 28 Dec 2025 20:19:55 GMT",
        "category": "tech"
      },
      {
        "title": "Top Wall Street analysts are confident about these 3 dividend-paying stocks",
        "link": "https://www.cnbc.com/2025/12/28/wall-street-analysts-are-confident-about-these-3-dividend-paying-stocks.html",
        "pubDate": "Sun, 28 Dec 2025 14:21:18 GMT",
        "category": "us"
      },
      {
        "title": "Restaurants&apos; hottest menu item in 2025 was &apos;value.&apos; That won&apos;t change next year",
        "link": "https://www.cnbc.com/2025/12/28/value-meals-restaurants-mcdonalds-chilis-taco-bell.html",
        "pubDate": "Sun, 28 Dec 2025 13:00:01 GMT",
        "category": "business"
      }
    ]
  }
}