{
  "updated_at": "2026-07-19T22:59:02.565584",
  "news": {
    "ap": [],
    "npr": [
      {
        "title": "America&apos;s 250th carries somber note for forcibly displaced Indigenous groups",
        "link": "https://www.npr.org/2026/07/19/nx-s1-5897600/americas-250th-carries-somber-note-for-forcibly-displaced-indigenous-groups",
        "pubDate": "Sun, 19 Jul 2026 17:54:37 -0400",
        "category": "us"
      },
      {
        "title": "A cavalcade of international stars headlined the World Cup&apos;s first-ever halftime final show",
        "link": "https://www.npr.org/2026/07/19/nx-s1-5888626/world-cup-halftime-final-show-bts-madonna-shakira-burna-boy-chris-martin-muppets-bieber",
        "pubDate": "Sun, 19 Jul 2026 17:29:52 -0400",
        "category": "Top News"
      },
      {
        "title": "Who is Andy Burnham, the U.K.&apos;s new prime minister?",
        "link": "https://www.npr.org/2026/07/19/g-s1-134001/andy-burnham-new-british-prime-minister",
        "pubDate": "Sun, 19 Jul 2026 12:00:00 -0400",
        "category": "world"
      },
      {
        "title": "Violence repeatedly erupts in dementia care despite warnings, inspections show",
        "link": "https://www.npr.org/2026/07/19/nx-s1-5894692/dementia-violence-warning-supervision-nursing-homes-assisted-living-facility",
        "pubDate": "Sun, 19 Jul 2026 07:00:00 -0400",
        "category": "health"
      },
      {
        "title": "An Israeli paraglider tries to save migrating swifts that nest in the Western Wall",
        "link": "https://www.npr.org/2026/07/19/nx-s1-5870684/israel-swift-birds-jerusalem",
        "pubDate": "Sun, 19 Jul 2026 06:00:00 -0400",
        "category": "Top News"
      },
      {
        "title": "Deadly overnight Russian attack on Ukraine targets the capital",
        "link": "https://www.npr.org/2026/07/19/nx-s1-5899518/russia-attack-kyiv",
        "pubDate": "Sun, 19 Jul 2026 05:14:38 -0400",
        "category": "Top News"
      },
      {
        "title": "5 clever design tricks to make a small home look bigger",
        "link": "https://www.npr.org/2026/07/19/nx-s1-5891817/5-clever-design-tricks-to-make-a-small-home-look-bigger",
        "pubDate": "Sun, 19 Jul 2026 05:01:00 -0400",
        "category": "Top News"
      },
      {
        "title": "Cuban artist and dissident exiled from country after 5 years in prison arrives in US",
        "link": "https://www.npr.org/2026/07/19/nx-s1-5899494/cuban-artist-exile-us",
        "pubDate": "Sun, 19 Jul 2026 03:27:59 -0400",
        "category": "Top News"
      },
      {
        "title": "MLS works to bring in a new generation of fans as the World Cup comes to an end",
        "link": "https://www.npr.org/2026/07/19/nx-s1-5899020/2026-world-cup-fifa-mls-major-league-soccer",
        "pubDate": "Sun, 19 Jul 2026 03:00:00 -0400",
        "category": "Top News"
      },
      {
        "title": "Spain is the 2026 World Cup champion, defeating Argentina for its 2nd title",
        "link": "https://www.npr.org/2026/07/19/nx-s1-5899071/2026-world-cup-fifa-argentina-spain-final-championship",
        "pubDate": "Sun, 19 Jul 2026 00:00:00 -0400",
        "category": "Top News"
      }
    ],
    "bbc": [
      {
        "title": "JD Vance announces birth of baby boy with wife Usha",
        "link": "https://www.bbc.co.uk/news/articles/cj63kngxpxpo?at_medium=RSS&amp;at_campaign=rss",
        "pubDate": "Sun, 19 Jul 2026 22:40:53 GMT",
        "category": "us"
      },
      {
        "title": "Burnham to promise 'more breathing room' for people in first speech as PM",
        "link": "https://www.bbc.co.uk/news/articles/cy8m7k98p3no?at_medium=RSS&amp;at_campaign=rss",
        "pubDate": "Sun, 19 Jul 2026 20:19:06 GMT",
        "category": "Top News"
      },
      {
        "title": "US soldier killed and one injured after Iranian attack in Iraq",
        "link": "https://www.bbc.co.uk/news/articles/cgk417jp83po?at_medium=RSS&amp;at_campaign=rss",
        "pubDate": "Sun, 19 Jul 2026 19:45:12 GMT",
        "category": "world"
      },
      {
        "title": "Thames Water lenders preparing legal challenge in event of Burnham nationalisation",
        "link": "https://www.bbc.co.uk/news/articles/cx278ed09nzo?at_medium=RSS&amp;at_campaign=rss",
        "pubDate": "Sun, 19 Jul 2026 18:35:16 GMT",
        "category": "business"
      },
      {
        "title": "Russia launches major ballistic missile attack on Ukrainian cities",
        "link": "https://www.bbc.co.uk/news/articles/c2el7xpnzrpo?at_medium=RSS&amp;at_campaign=rss",
        "pubDate": "Sun, 19 Jul 2026 18:25:40 GMT",
        "category": "Top News"
      },
      {
        "title": "The 1975's Matty Healy marries model Gabbriette Bechtel in Los Angeles",
        "link": "https://www.bbc.co.uk/news/articles/c5ywxp2d826o?at_medium=RSS&amp;at_campaign=rss",
        "pubDate": "Sun, 19 Jul 2026 14:50:11 GMT",
        "category": "Top News"
      },
      {
        "title": "Tate brothers arrested in US as further UK charges take total to 59",
        "link": "https://www.bbc.co.uk/news/articles/cwymly9yd33o?at_medium=RSS&amp;at_campaign=rss",
        "pubDate": "Sun, 19 Jul 2026 12:53:20 GMT",
        "category": "Top News"
      },
      {
        "title": "Neighbours actor Terence Donovan dies aged 90",
        "link": "https://www.bbc.co.uk/news/articles/crmrznw82j4o?at_medium=RSS&amp;at_campaign=rss",
        "pubDate": "Sun, 19 Jul 2026 08:18:32 GMT",
        "category": "Top News"
      },
      {
        "title": "I had to stop modelling because I kept passing out from crippling endometriosis",
        "link": "https://www.bbc.co.uk/news/articles/c79yyzw9v8xo?at_medium=RSS&amp;at_campaign=rss",
        "pubDate": "Sun, 19 Jul 2026 02:12:23 GMT",
        "category": "health"
      },
      {
        "title": "Record numbers of honours for working class heroes",
        "link": "https://www.bbc.co.uk/news/articles/cpd3dd3vv65o?at_medium=RSS&amp;at_campaign=rss",
        "pubDate": "Sun, 19 Jul 2026 01:56:10 GMT",
        "category": "Top News"
      }
    ],
    "reuters": [
      {
        "title": "Boos as Trump and Infantino enter the field for World Cup trophy ceremony",
        "link": "http://www.bing.com/news/apiclick.aspx?ref=FexRss&amp;aid=&amp;tid=6a5d56665c28479ca6461f5ec5532a33&amp;url=https%3a%2f%2fwww.reuters.com%2fsports%2fsoccer%2fboos-trump-infantino-enter-field-world-cup-trophy-ceremony-2026-07-19%2f&amp;c=14681840691720854007&amp;mkt=en-us",
        "pubDate": "Sun, 19 Jul 2026 15:53:00 GMT",
        "category": "Top News"
      },
      {
        "title": "Andrew, Tristan Tate arrested in US on new charges of rape, trafficking",
        "link": "http://www.bing.com/news/apiclick.aspx?ref=FexRss&amp;aid=&amp;tid=6a5d56665c28479ca6461f5ec5532a33&amp;url=https%3a%2f%2fwww.reuters.com%2fworld%2fus%2fus-marshals-arrest-hypermasculine-social-media-stars-andrew-tristan-tate-uk-2026-07-19%2f&amp;c=12015891011901948373&amp;mkt=en-us",
        "pubDate": "Sun, 19 Jul 2026 15:42:00 GMT",
        "category": "Top News"
      },
      {
        "title": "SpaceX moves Starship launch attempt to Thursday",
        "link": "http://www.bing.com/news/apiclick.aspx?ref=FexRss&amp;aid=&amp;tid=6a5d56665c28479ca6461f5ec5532a33&amp;url=https%3a%2f%2fwww.reuters.com%2fbusiness%2fmedia-telecom%2fspacex-moves-starship-launch-attempt-thursday-2026-07-19%2f&amp;c=14645883604484259773&amp;mkt=en-us",
        "pubDate": "Sun, 19 Jul 2026 15:25:00 GMT",
        "category": "Top News"
      },
      {
        "title": "US Vice President JD Vance announces birth of son",
        "link": "http://www.bing.com/news/apiclick.aspx?ref=FexRss&amp;aid=&amp;tid=6a5d56665c28479ca6461f5ec5532a33&amp;url=https%3a%2f%2fwww.reuters.com%2fworld%2fus%2fus-vice-president-jd-vance-announces-birth-son-2026-07-19%2f&amp;c=10874403159912755386&amp;mkt=en-us",
        "pubDate": "Sun, 19 Jul 2026 15:21:00 GMT",
        "category": "Top News"
      },
      {
        "title": "Shooting in Tucson, Arizona, leaves 10 people wounded, including suspect",
        "link": "http://www.bing.com/news/apiclick.aspx?ref=FexRss&amp;aid=&amp;tid=6a5d56665c28479ca6461f5ec5532a33&amp;url=https%3a%2f%2fwww.reuters.com%2fworld%2fus%2fshooting-tucson-arizona-leaves-10-people-wounded-including-suspect-2026-07-19%2f&amp;c=13318796361570736044&amp;mkt=en-us",
        "pubDate": "Sun, 19 Jul 2026 15:16:00 GMT",
        "category": "Top News"
      },
      {
        "title": "World Cup final between 10-man Argentina and Spain goes to extra time",
        "link": "http://www.bing.com/news/apiclick.aspx?ref=FexRss&amp;aid=&amp;tid=6a5d56665c28479ca6461f5ec5532a33&amp;url=https%3a%2f%2fwww.reuters.com%2fsports%2fsoccer%2fworld-cup-final-between-10-man-argentina-spain-goes-extra-time-2026-07-19%2f&amp;c=2953720597779500816&amp;mkt=en-us",
        "pubDate": "Sun, 19 Jul 2026 14:19:00 GMT",
        "category": "Top News"
      },
      {
        "title": "Madonna, BTS and Bieber bring star power to World Cup halftime show",
        "link": "http://www.bing.com/news/apiclick.aspx?ref=FexRss&amp;aid=&amp;tid=6a5d5669459f44bb8bfecd5a34657245&amp;url=https%3a%2f%2fwww.reuters.com%2fsports%2fsoccer%2fmadonna-bts-bieber-bring-star-power-world-cup-halftime-show-2026-07-19%2f&amp;c=10219302671735965931&amp;mkt=en-us",
        "pubDate": "Sun, 19 Jul 2026 14:01:00 GMT",
        "category": "world"
      },
      {
        "title": "With security lines and star-studded spectacle, World Cup prepares for final showdown",
        "link": "http://www.bing.com/news/apiclick.aspx?ref=FexRss&amp;aid=&amp;tid=6a5d56665c28479ca6461f5ec5532a33&amp;url=https%3a%2f%2fwww.reuters.com%2fsports%2fsoccer%2fwith-security-lines-star-studded-spectacle-world-cup-prepares-final-showdown-2026-07-19%2f&amp;c=414779718606983658&amp;mkt=en-us",
        "pubDate": "Sun, 19 Jul 2026 10:36:00 GMT",
        "category": "Top News"
      },
      {
        "title": "Jackson gains majority delegate support in Maine to challenge US Senator Collins, Politico reports",
        "link": "http://www.bing.com/news/apiclick.aspx?ref=FexRss&amp;aid=&amp;tid=6a5d56665c28479ca6461f5ec5532a33&amp;url=https%3a%2f%2fwww.reuters.com%2fworld%2fus%2fbellows-withdraws-us-senate-race-maine-democrats-regroup-2026-07-19%2f&amp;c=6096567452938297113&amp;mkt=en-us",
        "pubDate": "Sun, 19 Jul 2026 09:44:00 GMT",
        "category": "Top News"
      },
      {
        "title": "Boeing on track for 2028 Air Force One delivery, costs rise",
        "link": "http://www.bing.com/news/apiclick.aspx?ref=FexRss&amp;aid=&amp;tid=6a5d56665c28479ca6461f5ec5532a33&amp;url=https%3a%2f%2fwww.reuters.com%2fbusiness%2fautos-transportation%2fboeing-track-2028-air-force-one-delivery-costs-rise-2026-07-19%2f&amp;c=7919058179359717292&amp;mkt=en-us",
        "pubDate": "Sun, 19 Jul 2026 09:28:00 GMT",
        "category": "Top News"
      }
    ],
    "markets": [
      {
        "title": "U.S. death toll rises again as Iran war escalates over the weekend",
        "link": "https://www.cnbc.com/2026/07/19/us-says-it-targeted-iran-forces-after-deaths-of-two-american-troops.html",
        "pubDate": "Sun, 19 Jul 2026 20:25:15 GMT",
        "category": "world"
      },
      {
        "title": "Top Wall Street analysts suggest these 3 dividend stocks for steady income",
        "link": "https://www.cnbc.com/2026/07/19/top-analysts-suggest-these-3-dividend-stocks-for-steady-income.html",
        "pubDate": "Sun, 19 Jul 2026 12:46:25 GMT",
        "category": "us"
      },
      {
        "title": "Kalshi adds 3 million new users as prediction market capitalizes on the World Cup",
        "link": "https://www.cnbc.com/2026/07/19/kalshi-adds-3-million-new-users-as-company-capitalizes-on-world-cup.html",
        "pubDate": "Sun, 19 Jul 2026 12:42:30 GMT",
        "category": "Top News"
      },
      {
        "title": "American Airlines CEO lays out his vision to close a more than $3 billion profit gap",
        "link": "https://www.cnbc.com/2026/07/19/american-airlines-ceo.html",
        "pubDate": "Sun, 19 Jul 2026 12:00:01 GMT",
        "category": "business"
      }
    ]
  }
}