{
  "updated_at": "2026-06-07T19:42:40.897071",
  "news": {
    "ap": [],
    "npr": [
      {
        "title": "Alexander Zverev wins the French Open to finally earn a 1st Grand Slam title",
        "link": "https://www.npr.org/2026/06/07/g-s1-126803/french-open-2026-alexander-zverev-grand-slam-title",
        "pubDate": "Sun, 07 Jun 2026 14:21:03 -0400",
        "category": "world"
      },
      {
        "title": "U.K. deputy prime minister: JD Vance was wrong to blame teen&apos;s murder on  immigration",
        "link": "https://www.npr.org/2026/06/07/nx-s1-5849212/u-k-deputy-prime-minister-jd-vance-was-wrong-to-blame-teens-murder-on-immigration",
        "pubDate": "Sun, 07 Jun 2026 11:39:52 -0400",
        "category": "Top News"
      },
      {
        "title": "Armenians vote in general election watched closely by Russia and the West",
        "link": "https://www.npr.org/2026/06/07/nx-s1-5849210/armenians-vote-general-election-russia-west",
        "pubDate": "Sun, 07 Jun 2026 11:30:44 -0400",
        "category": "Top News"
      },
      {
        "title": "Texas has detected a flesh-eating parasite in livestock after 60 years",
        "link": "https://www.npr.org/2026/06/07/nx-s1-5846844/texas-has-detected-a-flesh-eating-parasite-in-livestock-after-60-years",
        "pubDate": "Sun, 07 Jun 2026 09:21:20 -0400",
        "category": "health"
      },
      {
        "title": "Virginia&apos;s data center boom is raising West Virginia&apos;s electricity bills",
        "link": "https://www.npr.org/2026/06/07/nx-s1-5828398/virginias-data-center-boom-is-raising-west-virginias-electricity-bills",
        "pubDate": "Sun, 07 Jun 2026 09:21:16 -0400",
        "category": "us"
      },
      {
        "title": "It&apos;s one of the world&apos;s most isolated islands. Here come the bulldozers",
        "link": "https://www.npr.org/2026/06/07/g-s1-125586/island-isolated-india-great-nicobar-china-development",
        "pubDate": "Sun, 07 Jun 2026 07:51:18 -0400",
        "category": "Top News"
      },
      {
        "title": "1 million people flood Madrid streets to see the pope&apos;s flower-carpeted procession",
        "link": "https://www.npr.org/2026/06/07/nx-s1-5849147/1-million-flood-madrid-streets-pope-procession",
        "pubDate": "Sun, 07 Jun 2026 06:51:01 -0400",
        "category": "Top News"
      },
      {
        "title": "Police search for suspects in Ohio shooting that wounded 12 near a street festival",
        "link": "https://www.npr.org/2026/06/07/nx-s1-5849137/12-people-shot-ohio-festival",
        "pubDate": "Sun, 07 Jun 2026 06:02:05 -0400",
        "category": "Top News"
      },
      {
        "title": "4 takeaways from the U.S. men&apos;s final tune-up games before the World Cup",
        "link": "https://www.npr.org/2026/06/07/nx-s1-5848725/2026-world-cup-usmnt-preview",
        "pubDate": "Sun, 07 Jun 2026 06:00:00 -0400",
        "category": "Top News"
      },
      {
        "title": "When U.S. foreign aid changed, AIDS workers in Africa felt it",
        "link": "https://www.npr.org/2026/06/07/nx-s1-5837324/usaid-aids-africa",
        "pubDate": "Sun, 07 Jun 2026 06:00:00 -0400",
        "category": "Top News"
      }
    ],
    "bbc": [
      {
        "title": "Zelensky in Downing Street for Ukraine war talks with European leaders",
        "link": "https://www.bbc.com/news/articles/cr7xr1g3nvvo?at_medium=RSS&amp;at_campaign=rss",
        "pubDate": "Sun, 07 Jun 2026 18:49:17 GMT",
        "category": "world"
      },
      {
        "title": "Christian Eriksen conscious after collapsing in Denmark game",
        "link": "https://www.bbc.com/sport/football/articles/czrxgd2nljno?at_medium=RSS&amp;at_campaign=rss",
        "pubDate": "Sun, 07 Jun 2026 18:31:56 GMT",
        "category": "Top News"
      },
      {
        "title": "Royal Mail delivers new parent magazine to father 19 years late",
        "link": "https://www.bbc.com/news/articles/cx2dl7kwex0o?at_medium=RSS&amp;at_campaign=rss",
        "pubDate": "Sun, 07 Jun 2026 15:33:44 GMT",
        "category": "Top News"
      },
      {
        "title": "M&S launches new traineeship for 1,000 young people",
        "link": "https://www.bbc.com/news/articles/cr7xr3dvxp9o?at_medium=RSS&amp;at_campaign=rss",
        "pubDate": "Sun, 07 Jun 2026 12:16:11 GMT",
        "category": "Top News"
      },
      {
        "title": "Lammy says he told JD Vance his Nowak comments were 'wrong'",
        "link": "https://www.bbc.com/news/articles/cjwg387040wo?at_medium=RSS&amp;at_campaign=rss",
        "pubDate": "Sun, 07 Jun 2026 10:50:04 GMT",
        "category": "Top News"
      },
      {
        "title": "Hegseth attacks Europe over migration with beach 'invasion' D-Day speech",
        "link": "https://www.bbc.com/news/articles/c802e7jk458o?at_medium=RSS&amp;at_campaign=rss",
        "pubDate": "Sun, 07 Jun 2026 10:35:25 GMT",
        "category": "us"
      },
      {
        "title": "Steve Rosenberg: Russia's economic forum overshadowed by drone attacks on St Petersburg",
        "link": "https://www.bbc.com/news/articles/c9q2gp52rgro?at_medium=RSS&amp;at_campaign=rss",
        "pubDate": "Sun, 07 Jun 2026 07:11:18 GMT",
        "category": "Top News"
      },
      {
        "title": "I was applying for hundreds of jobs - this tip helped me get one",
        "link": "https://www.bbc.com/news/articles/cd7pqwr5lqxo?at_medium=RSS&amp;at_campaign=rss",
        "pubDate": "Sat, 06 Jun 2026 23:39:00 GMT",
        "category": "business"
      },
      {
        "title": "The gamers taking on the industry to stop it switching off games",
        "link": "https://www.bbc.com/news/articles/c8e8e7g0r82o?at_medium=RSS&amp;at_campaign=rss",
        "pubDate": "Sat, 06 Jun 2026 23:25:51 GMT",
        "category": "tech"
      },
      {
        "title": "Cosmeticorexia: How girls are falling down a skincare rabbit hole",
        "link": "https://www.bbc.com/news/articles/cx212x41evwo?at_medium=RSS&amp;at_campaign=rss",
        "pubDate": "Sat, 06 Jun 2026 23:06:33 GMT",
        "category": "health"
      }
    ],
    "reuters": [],
    "markets": [
      {
        "title": "100 days of the Iran war: How global markets and the economy have been affected, in charts",
        "link": "https://www.cnbc.com/2026/06/07/iran-war-100-days-trump-stocks-sp500-bonds-oil.html",
        "pubDate": "Sun, 07 Jun 2026 05:00:01 GMT",
        "category": "world"
      }
    ]
  }
}