{
  "updated_at": "2026-07-13T11:22:15.947380",
  "news": {
    "ap": [
      {
        "title": "McConnell says a fall led to his hospitalization, breaking weeks of silence about health condition",
        "link": "http://www.bing.com/news/apiclick.aspx?ref=FexRss&amp;aid=&amp;tid=6a54c9a24feb43f699cb580bea374c45&amp;url=https%3a%2f%2fapnews.com%2farticle%2fmitch-mcconnell-hospitalized-fall-health-senate-d708e9a1f18763fbb961fd3879227ce3&amp;c=17721607014935953307&amp;mkt=en-us",
        "pubDate": "Sun, 12 Jul 2026 16:03:00 GMT",
        "category": "business"
      },
      {
        "title": "What to know about new rules and technology behind the World Cup\u2019s most contentious calls",
        "link": "http://www.bing.com/news/apiclick.aspx?ref=FexRss&amp;aid=&amp;tid=6a54c9a54e114dada5073892fd67b9e3&amp;url=https%3a%2f%2fapnews.com%2farticle%2fworld-cup-embolo-mistaken-identity-argentina-switzerland-399f2ee88e27264cba6f34ac24181b5a&amp;c=10804809108055307186&amp;mkt=en-us",
        "pubDate": "Sun, 12 Jul 2026 15:02:00 GMT",
        "category": "tech"
      }
    ],
    "npr": [
      {
        "title": "Houston community holds vigil for man killed by ICE agents",
        "link": "https://www.npr.org/2026/07/13/nx-s1-5890966/houston-community-holds-vigil-for-man-killed-by-ice-agents",
        "pubDate": "Mon, 13 Jul 2026 07:08:47 -0400",
        "category": "us"
      },
      {
        "title": "Pythons&apos; extreme biology may hold clues for treating human disease",
        "link": "https://www.npr.org/2026/07/13/nx-s1-5887668/pythons-metabolism-digestion-human-disease-treatment",
        "pubDate": "Mon, 13 Jul 2026 06:00:00 -0400",
        "category": "health"
      },
      {
        "title": "How federal prison guards stop lawsuits before they start",
        "link": "https://www.npr.org/2026/07/13/nx-s1-5825915/prison-grievance-retaliation-complaints",
        "pubDate": "Mon, 13 Jul 2026 05:10:00 -0400",
        "category": "Top News"
      },
      {
        "title": "EV battery recycling has an economics problem. Colorado has a solution",
        "link": "https://www.npr.org/2026/07/13/nx-s1-5847025/ev-battery-recycling-economics",
        "pubDate": "Mon, 13 Jul 2026 05:00:00 -0400",
        "category": "business"
      },
      {
        "title": "He was having a mental health crisis. Memphis task force agents came and shot him",
        "link": "https://www.npr.org/2026/07/13/nx-s1-5888618/memphis-safe-task-force-shooting-jonah-neal",
        "pubDate": "Mon, 13 Jul 2026 05:00:00 -0400",
        "category": "Top News"
      },
      {
        "title": "Eat your ice cream for a long, healthy life? This doctor says so",
        "link": "https://www.npr.org/2026/07/13/nx-s1-5884664/zeke-emanuel-optimize-health-long-life",
        "pubDate": "Mon, 13 Jul 2026 05:00:00 -0400",
        "category": "Top News"
      },
      {
        "title": "Morning news brief",
        "link": "https://www.npr.org/2026/07/13/nx-s1-5885745/morning-news-brief",
        "pubDate": "Mon, 13 Jul 2026 04:48:40 -0400",
        "category": "Top News"
      },
      {
        "title": "Sam Neill, known for &apos;Jurassic Park&apos; and &apos;The Piano,&apos; dies at 78, his family says",
        "link": "https://www.npr.org/2026/07/13/nx-s1-5891505/actor-sam-neill-dies",
        "pubDate": "Mon, 13 Jul 2026 03:20:30 -0400",
        "category": "world"
      },
      {
        "title": "McConnell says a fall led to his hospitalization, breaking weeks of silence",
        "link": "https://www.npr.org/2026/07/13/nx-s1-5891492/mcconnell-fall-hospitalization",
        "pubDate": "Mon, 13 Jul 2026 01:49:09 -0400",
        "category": "Top News"
      },
      {
        "title": "Want to own a real T. rex? It could cost you $30 million",
        "link": "https://www.npr.org/2026/07/12/nx-s1-5890988/t-rex-gus-dinosaur-auction-sothebys-millions",
        "pubDate": "Sun, 12 Jul 2026 20:14:03 -0400",
        "category": "Top News"
      }
    ],
    "bbc": [
      {
        "title": "At least 27 killed, 25 critically injured after fire engulfs Bangkok bar",
        "link": "https://www.bbc.co.uk/news/articles/c24yev53q06o?at_medium=RSS&amp;at_campaign=rss",
        "pubDate": "Mon, 13 Jul 2026 11:10:58 GMT",
        "category": "world"
      },
      {
        "title": "UK seeking extradition of man suspected of killing wife and two daughters",
        "link": "https://www.bbc.co.uk/news/articles/cy8w61qz873o?at_medium=RSS&amp;at_campaign=rss",
        "pubDate": "Mon, 13 Jul 2026 10:48:04 GMT",
        "category": "Top News"
      },
      {
        "title": "Footage appears to show Ann Widdecombe murder suspect getting into car on morning of attack",
        "link": "https://www.bbc.co.uk/news/articles/c0mydjl12mwo?at_medium=RSS&amp;at_campaign=rss",
        "pubDate": "Mon, 13 Jul 2026 10:29:22 GMT",
        "category": "Top News"
      },
      {
        "title": "Heatwave to intensify in second week as wildfires burn across UK",
        "link": "https://www.bbc.co.uk/weather/articles/c0jyx16ww8jo?at_medium=RSS&amp;at_campaign=rss",
        "pubDate": "Mon, 13 Jul 2026 10:04:04 GMT",
        "category": "Top News"
      },
      {
        "title": "Witness says he crawled for exit as flames swept through Bangkok bar",
        "link": "https://www.bbc.co.uk/news/articles/crr8gnx01d7o?at_medium=RSS&amp;at_campaign=rss",
        "pubDate": "Mon, 13 Jul 2026 10:02:43 GMT",
        "category": "Top News"
      },
      {
        "title": "More than 2,700 people may have died in exceptional May and June heatwaves in England and Wales",
        "link": "https://www.bbc.co.uk/news/articles/czx5zy82n7no?at_medium=RSS&amp;at_campaign=rss",
        "pubDate": "Mon, 13 Jul 2026 08:57:15 GMT",
        "category": "health"
      },
      {
        "title": "10 years of Pok\u00e9mon Go and the millions still trying to catch 'em all",
        "link": "https://www.bbc.co.uk/news/articles/cevlwk4nrm7o?at_medium=RSS&amp;at_campaign=rss",
        "pubDate": "Mon, 13 Jul 2026 00:07:00 GMT",
        "category": "tech"
      },
      {
        "title": "New era for Gibraltar with removal of 118-year-old border controls with Spain",
        "link": "https://www.bbc.co.uk/news/articles/cwydz60j3eno?at_medium=RSS&amp;at_campaign=rss",
        "pubDate": "Sun, 12 Jul 2026 23:29:06 GMT",
        "category": "Top News"
      },
      {
        "title": "How to change bank, energy or broadband provider and save money",
        "link": "https://www.bbc.co.uk/news/articles/cd7w98n2y3eo?at_medium=RSS&amp;at_campaign=rss",
        "pubDate": "Sun, 12 Jul 2026 23:28:01 GMT",
        "category": "business"
      },
      {
        "title": "From Trump critic to ally, Lindsey Graham was a political survivor of the Maga era",
        "link": "https://www.bbc.co.uk/news/articles/clyrdn216k2o?at_medium=RSS&amp;at_campaign=rss",
        "pubDate": "Sun, 12 Jul 2026 19:42:26 GMT",
        "category": "us"
      }
    ],
    "reuters": [],
    "markets": []
  }
}